vimfected/__init__.py
vimfected/__main__.py
vimfected/game.py
vimfected/locals.py
vimfected/player.py
vimfected/sprites.py
vimfected/utils.py
vimfected/assets/__init__.py
vimfected/assets/__pycache__/__init__.cpython-38.pyc
vimfected-0.1.0.dev0.dist-info/LICENSE
vimfected-0.1.0.dev0.dist-info/METADATA
vimfected-0.1.0.dev0.dist-info/WHEEL
vimfected-0.1.0.dev0.dist-info/entry_points.txt
vimfected-0.1.0.dev0.dist-info/top_level.txt
vimfected-0.1.0.dev0.dist-info/RECORD
